{
    "title": "ජය පිරිත",
    "content": "<p style='text-align:center'>සිරි ධිති මති තේජෝ ජය&shy;සිද්ධි මහිද්ධි මහා ගුණං අප&shy;රි&shy;මිත</p><p style='text-align:center'>පුඤ්ඤාධි කාරස්ස සබ්බ&shy;න්ත&shy;රාය නිවා&shy;රණ සම&shy;ත්ථස්ස,</p><p style='text-align:center'>භග&shy;වතෝ අර&shy;හතෝ සම්මා සම්බු&shy;ද්ධස්ස</p><p style='text-align:center'>ද්විත්තිංස මහා පුරි&shy;ස&shy;ල&shy;ක්ඛ&shy;ණා&shy;නු&shy;භා&shy;වේන අසී&shy;ත්&zwj;ය&shy;නු&shy;ව්&zwj;ය&shy;ඤ්ජන</p><p style='text-align:center'>ලක්ඛ&shy;ණා&shy;නු&shy;භා&shy;වේන අට්ඨු&shy;ත්ත&shy;ර&shy;ස&shy;ත&shy;මං&shy;ගල ලක්ඛ&shy;ණානු භාවේන,</p><p style='text-align:center'>ඡබ්බණ්ණ රස්&zwj;යා&shy;නු&shy;භා&shy;වේන කෙතු&shy;මා&shy;ලා&shy;නු&shy;භා&shy;වේන</p><p style='text-align:center'>දස&shy;ප&shy;ර&shy;මි&shy;තා&shy;නු&shy;භා&shy;වේන,දස උප&shy;පා&shy;ර&shy;මි&shy;තානු භාවේන,</p><p style='text-align:center'>දස&shy;ප&shy;ර&shy;ම&shy;ත්ථ&shy;පා&shy;ර&shy;මි&shy;තා&shy;නු&shy;භා&shy;වේන, සීල සමාධි පඤ්ඤා&shy;නු&shy;භා&shy;වේන,</p><p style='text-align:center'>බුද්ධා&shy;නු&shy;භා&shy;වේන, ධම්මා&shy;නු&shy;භා&shy;වේන,සංඝා&shy;නු&shy;භා&shy;වේන</p><p style='text-align:center'>තේජා&shy;නු&shy;භා&shy;වේන,ඉධ්&zwj;යා&shy;නු&shy;භා&shy;වේන,බලා&shy;නු&shy;භා&shy;වේන,</p><p style='text-align:center'>ඤෙය්&zwj;ය&shy;ධ&shy;ම්මා&shy;නු&shy;භා&shy;වේන,චතු&shy;රා&shy;සී&shy;ති&shy;ස&shy;හස්ස</p><p style='text-align:center'>ධම්ම&shy;ක්ඛ&shy;න්ධා&shy;නු&shy;භා&shy;වේන නව&shy;ලෝ&shy;කෝ&shy;ත්තර</p><p style='text-align:center'>ධම්මා&shy;නු&shy;භා&shy;වේන,අට්ඨං&shy;ගි&shy;ක&shy;ම&shy;ග්ගානු-භවේන,</p><p style='text-align:center'>අට්ඨ&shy;ස&shy;මා&shy;ප&shy;ත්&zwj;යා&shy;නු&shy;භා&shy;වේන,ජල&shy;භි&shy;ඤ්ඤා&shy;නු&shy;භා&shy;වේන,</p><p style='text-align:center'>මෙත්තා,කරුණා,මුදිතා,උපේ&shy;ක්ඛා&shy;නු&shy;භා&shy;වේන,</p><p style='text-align:center'>සබ්බ&shy;පා&shy;ර&shy;මි&shy;තා&shy;නු&shy;භා&shy;වේන,රත&shy;න&shy;ත්තය සර&shy;ණා&shy;නු&shy;භා&shy;වේන</p><p style='text-align:center'>තුය්හං සබ්බ&shy;රෝග සෝක උප&shy;ද්දව දුක්ඛ&shy;දෝ&shy;ම&shy;න&shy;ස්සු&shy;පා&shy;යාසා</p><p style='text-align:center'>වින&shy;ස්සන්තු, සබ්බ&shy;සං&shy;කප්පා තුය්හං දමි&shy;ජ්ඣන්තු.</p><p style='text-align:center'>දීඝා&shy;යුකෝ හෝතු සච&shy;ව&shy;ස්ස&shy;ජි&shy;වේන සමං&shy;ගිකෝ හෝතු සබ්බදා</p><p style='text-align:center'>ආකාස පබ්බත වන භූමි&shy;ත&shy;ටා&shy;ක&shy;ගංගා මහා සමුද්ද</p><p style='text-align:center'>ආර&shy;ක්ඛක දේවතා සදා තුම්හෙ අනු&shy;ර&shy;ක්ඛන්තු,සබ්බ</p><p style='text-align:center'>බුද්ධා&shy;නු&shy;භා&shy;වේන සබ්බ ධම්මා&shy;නු&shy;භා&shy;වේන සබ්බ සංඝා&shy;නු&shy;භා&shy;වේන,</p><p style='text-align:center'>බුද්ධ&shy;ර&shy;තනං ධම්ම&shy;ර&shy;තනං සංඝ&shy;ර&shy;තනං තින්නං රත&shy;නානං</p><p style='text-align:center'>ආනු&shy;භා&shy;වේන චතු&shy;රා&shy;සීති සහස්ස ධම්ම&shy;ක්ඛ&shy;නා&shy;ධානු භාවේන,</p><p style='text-align:center'>බි&zwj;ටක&shy;ත්ත&shy;යානු භාවේන,ජින&shy;සා&shy;ව&shy;කා&shy;නු&shy;භා&shy;වේන,</p><p style='text-align:center'>සබ්බේතේ රෝගා, සබ්බේ තේ භයා, සබ්බේ &zwj;තේ අන්ත&shy;රායා,</p><p style='text-align:center'>සබ්බේ තේ උප්ප&shy;දවා,සබ්බේ තෙ දුන් නිමිත්තා,</p><p style='text-align:center'>සබ්බේ තේ අව&shy;මං&shy;ගලා වින&shy;ස්සන්තු</p><p style='text-align:center'>ආයු&shy;ව&shy;ඩ්ඪකෝ,ධන&shy;ව&shy;ඩ්ඪකෝ,සිරි&shy;ව&shy;ඩ්ඪකෝ,යස&shy;ව&shy;ඩ්ඪකෝ,</p><p style='text-align:center'>බල&shy;ව&shy;ඩ්ඪකෝ,වණ්ණ&shy;ව&shy;ඩ්ඪකෝ,සුඛ&shy;ව&shy;ඩ්ඪකෝ,හෝතු සබ්බදා</p><p style='text-align:center'>දුක්ඛ&shy;රෝ&shy;ග&shy;භ&shy;යා&shy;වේරා-සෝකා සබ්බේ උප&shy;ද්දවා</p><p style='text-align:center'>අනේකා අන්ත&shy;රා&shy;යාපි-වින&shy;ස්සන්තු ච තේජසා</p><p style='text-align:center'>ජය සිද්ධි ධනං ලාභං_ සොත්ථි&shy;භාග්&zwj;යං සුඛං බලං</p><p style='text-align:center'>සිරි ආයු ච වණ්ණෝ ච -භෝගං චුද්ධි ච යසවා</p><p style='text-align:center'>සත&shy;වස්සා ච ආයු ච-ජීව&shy;සි&shy;ද්ධි&shy;භ&shy;වන්තු තේ</p>",
    "suggestions": [
        {
            "id": "mahamangalasutta",
            "title": "මහා මංගල සූත්‍ර‍ය"
        },
        {
            "id": "rathanasutta",
            "title": "රතන සූත්‍රය"
        }
    ]
}